firecrest_executor.py
firecrest_executor-0.3.1.dist-info/licenses/LICENSE
firecrest_executor-0.3.1.dist-info/METADATA
firecrest_executor-0.3.1.dist-info/WHEEL
firecrest_executor-0.3.1.dist-info/top_level.txt
firecrest_executor-0.3.1.dist-info/RECORD
