Metadata-Version: 2.4
Name: firecrest-executor
Version: 0.3.1
Summary: Execute python functions on a remote supercomputer
Author-email: Joost VandeVondele <Joost.VandeVondele@gmail.com>
License: Apache-2.0
Project-URL: Homepage, https://github.com/vondele/firecrest-executor
Project-URL: Repository, https://github.com/vondele/firecrest-executor
Keywords: HPC,supercomputing,executor,firecrest
Classifier: Development Status :: 4 - Beta
Classifier: Programming Language :: Python
Requires-Python: >=3.8
License-File: LICENSE
Requires-Dist: pyfirecrest>=3.2.2
Requires-Dist: dill>=0.3.9
Provides-Extra: examples
Requires-Dist: nevergrad; extra == "examples"
Dynamic: license-file
